LICENSE.txt
MANIFEST.in
README.rst
osql-cli
osql-cli.bat
setup.cfg
setup.py
osql_cli.egg-info/PKG-INFO
osql_cli.egg-info/SOURCES.txt
osql_cli.egg-info/dependency_links.txt
osql_cli.egg-info/requires.txt
osql_cli.egg-info/top_level.txt
osqlcli/__init__.py
osqlcli/completion_refresher.py
osqlcli/config.py
osqlcli/decorators.py
osqlcli/encodingutils.py
osqlcli/filters.py
osqlcli/key_bindings.py
osqlcli/main.py
osqlcli/osql_cli.py
osqlcli/osqlbuffer.py
osqlcli/osqlcliclient.py
osqlcli/osqlclioptionsparser.py
osqlcli/osqlcompleter.py
osqlcli/osqlqueries_mssql.py
osqlcli/osqlqueries_oracle.py
osqlcli/osqlqueries_sqlite.py
osqlcli/osqlstyle.py
osqlcli/osqltoolbar.py
osqlcli/packages/__init__.py
osqlcli/packages/prioritization.py
osqlcli/packages/sqlcompletion.py
osqlcli/packages/osqlliterals/__init__.py
osqlcli/packages/osqlliterals/main.py
osqlcli/packages/parseutils/__init__.py
osqlcli/packages/parseutils/ctes.py
osqlcli/packages/parseutils/meta.py
osqlcli/packages/parseutils/tables.py
osqlcli/packages/parseutils/utils.py
osqlcli/packages/special/__init__.py
osqlcli/packages/special/commands.py
osqlcli/packages/special/commands_oracle.py
osqlcli/packages/special/main.py
osqlcli/packages/special/namedqueries.py